{
  "po" : 
  {
    "en_US" : 
    {
      "branch" : "",
      "commit" : 
      {
        "date" : "",
        "hash" : "",
        "title" : ""
      }
    },
    "zh_CN" : 
    {
      "branch" : "master",
      "commit" : 
      {
        "date" : "2025-11-17 23:27:24 +0000",
        "hash" : "6bf7fadc295a862f1f4b2f2d4a9c4c0b1e998dff",
        "title" : "Merge pull request #2943 from ehuss/config-changelog"
      }
    },
    "zh_TW" : 
    {
      "branch" : "master",
      "commit" : 
      {
        "date" : "2025-11-17 23:27:24 +0000",
        "hash" : "6bf7fadc295a862f1f4b2f2d4a9c4c0b1e998dff",
        "title" : "Merge pull request #2943 from ehuss/config-changelog"
      }
    }
  },
  "pot" : 
  {
    "branch" : "master",
    "commit" : 
    {
      "date" : "2025-11-17 23:27:24 +0000",
      "hash" : "6bf7fadc295a862f1f4b2f2d4a9c4c0b1e998dff",
      "title" : "Merge pull request #2943 from ehuss/config-changelog"
    }
  },
  "type" : "branch",
  "version" : "master"
}